LICENSE.txt
README.md
setup.cfg
setup.py
rainyday/__init__.py
rainyday/rainyday.py
rainyday.egg-info/PKG-INFO
rainyday.egg-info/SOURCES.txt
rainyday.egg-info/dependency_links.txt
rainyday.egg-info/requires.txt
rainyday.egg-info/top_level.txt