Metadata-Version: 2.1
Name: rainyday
Version: 1.0
Summary: Weather forecast for up to 12 hours.
Home-page: https://github.com/saifanwer
Author: Mohammad Saif Anwer
Author-email: saifdavinci@gmail.com
License: MIT
Download-URL: https://github.com/saifanwer/OOP11/archive/refs/tags/v1.0.tar.gz
Keywords: OpenWeather,Forecast,Weather
Platform: UNKNOWN
Classifier: Development Status :: 3 - Alpha
Classifier: Intended Audience :: Developers
Classifier: Topic :: Software Development :: Build Tools
Classifier: License :: OSI Approved :: MIT License
Classifier: Programming Language :: Python :: 3
Classifier: Programming Language :: Python :: 3.4
Classifier: Programming Language :: Python :: 3.5
Classifier: Programming Language :: Python :: 3.6
Classifier: Programming Language :: Python :: 3.7
Classifier: Programming Language :: Python :: 3.8
Classifier: Programming Language :: Python :: 3.9
Classifier: Programming Language :: Python :: 3.10
License-File: LICENSE.txt
